Workbook
Name x4_cogs_var: 'Параметри ЛР4'!$C$2
Name x4_gm: 'Параметри ЛР4'!$C$3
Name x4_scale: 'Параметри ЛР4'!$C$4
Name x4_readings: 'Параметри ЛР4'!$C$5
Name x4_sim: 'Параметри ЛР4'!$C$6
Name x4_sms_cost: 'Параметри ЛР4'!$C$7
Name x4_sms_typ: 'Параметри ЛР4'!$C$8
Name x4_sup_h: 'Параметри ЛР4'!$C$9
Name x4_sup_rate: 'Параметри ЛР4'!$C$10
Name x4_sms_incl: 'Параметри ЛР4'!$C$11
Name x4_sms_price: 'Параметри ЛР4'!$C$12
Name x4_sms_high: 'Параметри ЛР4'!$C$13
Name x4_sup_high: 'Параметри ЛР4'!$C$14
Name x4_fee: 'Параметри ЛР4'!$C$15
Name x4_high_share: 'Параметри ЛР4'!$C$16
Name x4_value: 'Параметри ЛР4'!$C$17
Name x4_energy: 'Параметри ЛР4'!$C$18
Name x4_gain: 'Параметри ЛР4'!$C$19
Name x4_episode: 'Параметри ЛР4'!$C$20
Name x4_cogs: 'Параметри ЛР4'!$C$22
Name x4_cogs_high: 'Параметри ЛР4'!$C$23
Name x4_over: 'Параметри ЛР4'!$C$24
Name x4_floor_unit: 'Параметри ЛР4'!$C$25
Name x4_mix_B: 'Тарифи'!$C$5
Name x4_use_B: 'Тарифи'!$C$6
Name x4_base_B: 'Тарифи'!$C$2
Name x4_pb_B: 'Тарифи'!$C$3
Name x4_cc_B: 'Тарифи'!$C$8
Name x4_mix_S: 'Тарифи'!$D$5
Name x4_use_S: 'Тарифи'!$D$6
Name x4_base_S: 'Тарифи'!$D$2
Name x4_pb_S: 'Тарифи'!$D$3
Name x4_cc_S: 'Тарифи'!$D$8
Name x4_mix_P: 'Тарифи'!$E$5
Name x4_use_P: 'Тарифи'!$E$6
Name x4_base_P: 'Тарифи'!$E$2
Name x4_pb_P: 'Тарифи'!$E$3
Name x4_cc_P: 'Тарифи'!$E$8

Sheet Параметри ЛР4
A1: Ім'я | B1: Показник | C1: Значення | D1: Одиниця | E1: Тип | F1: Пояснення
A2: x4_cogs_var | B2: COGS на будівлю за варіантом | C2: 16 | D2: EUR/міс. | E2: Д | F2: варіант 14, ЛР № 4
A3: x4_gm | B3: Target gross margin | C3: 0.7 | D3: частка | E3: Д | F3: варіант 14
A4: x4_scale | B4: Масштаб Y3 | C4: 85 | D4: будівель/міс. | E4: Д | F4: варіант 14
A5: x4_readings | B5: Обробка і зберігання показів | C5: 6.48 | D5: EUR/буд./міс. | E5: Д | F5: ЛР № 1: 86 400 показів × 0,075 / 1000
A6: x4_sim | B6: Мобільний зв'язок шлюзу | C6: 4 | D6: EUR/буд./міс. | E6: Д | F6: ЛР № 1
A7: x4_sms_cost | B7: Собівартість SMS | C7: 0.06 | D7: EUR | E7: Д | F7: ЛР № 1
A8: x4_sms_typ | B8: SMS на будівлю, типово | C8: 12 | D8: шт./міс. | E8: Д | F8: ЛР № 1
A9: x4_sup_h | B9: Підтримка на будівлю, типово | C9: 0.16 | D9: год/міс. | E9: Д | F9: ЛР № 1
A10: x4_sup_rate | B10: Вартість години підтримки | C10: 30 | D10: EUR/год | E10: Д | F10: ЛР № 1
A11: x4_sms_incl | B11: SMS, включені на будівлю | C11: 20 | D11: шт./міс. | E11: П | F11: тарифне правило
A12: x4_sms_price | B12: Ціна SMS понад ліміт | C12: 0.25 | D12: EUR | E12: П | F12: не нижче floor 0,20
A13: x4_sms_high | B13: SMS у будівлі з high usage | C13: 40 | D13: шт./міс. | E13: П | F13: A3
... A20: x4_episode | B20: Тривалість епізоду нестабільності | C20: 12 | D20: міс. | E20: П | F20: A9
A22: x4_cogs | B22: COGS на будівлю з компонентів ЛР № 1 | C22: =x4_readings+x4_sim+x4_sms_cost*x4_sms_typ+x4_sup_h*x4_sup_rate | D22: EUR/буд./міс. | E22: Р | F22: =IF(ABS(C22-x4_cogs_var)<0.001,"збігається з варіантом","розбіжність")
A23: x4_cogs_high | B23: COGS будівлі з high usage | C23: =x4_cogs+(x4_sms_high-x4_sms_typ)*x4_sms_cost+(x4_sup_high-x4_sup_h)*x4_sup_rate | D23: EUR/буд./міс. | E23: Р | F23: A3
A24: x4_over | B24: Overage з будівлі з high usage | C24: =x4_fee+MAX(x4_sms_high-x4_sms_incl,0)*x4_sms_price | D24: EUR/буд./міс. | E24: Р | F24: доплата + SMS понад ліміт
A25: x4_floor_unit | B25: Floor price на будівлю | C25: =x4_cogs_var/(1-x4_gm) | D25: EUR/буд./міс. | E25: Р | F25: COGS / (1 − GM)

Sheet Журнал припущень
A1: ID | B1: Припущення | C1: Значення | D1: Підстава | E1: Що змінює
A2: A1 | B2: Розподіл клієнтів за тарифами | C2: Basic 60%, Standard 30%, Pro 10% клієнтів | D2: П: сегмент S1 ЛР № 1 складається переважно з власників однієї будівлі; керуючі компанії з портфелем є меншістю | E2: Revenue і COGS
A3: A2 | B3: Середнє usage | C3: будівель на клієнта: Basic 1,0; Standard 2,0; Pro 5,0 (у середньому 1,7); на будівлю до 30 точок обліку, 12 SMS, 0,16 год підтримки | D3: П: типова будівля і v = 16 EUR з ЛР № 1; межа 30 лічильників з ЛР № 2 | E3: COGS і margin
A4: A3 | B4: Високе usage | C4: 10% будівель у стані «нестабільний облік»: 0,6 год підтримки і 40 SMS на місяць; клієнт Pro з 20 будівлями | D4: П: поріг пропусків 10% з A5 ЛР № 1, ризик варіанта ЛР № 3 | E4: ризик тарифу
A5: A4 | B5: COGS на одного клієнта (базова частина) | C5: Basic 0,10 год, Standard 0,20 год, Pro 0,50 год × 30 EUR = 3, 6, 15 EUR на місяць | D5: П: адміністрування акаунта, рахунок, ролі, для Pro пріоритетна підтримка і квартальний огляд | E5: COGS бази
A6: A5 | B6: Розрахунковий період і валюта | C6: календарний місяць, EUR, ціни без ПДВ | D6: Д: варіант задає COGS у EUR за місяць | E6: усі суми
A7: A6 | B7: Підключення будівлі | C7: шлюз і монтаж оплачуються разово за собівартістю, поза місячною моделлю | D7: П: обладнання не входить у v = 16 EUR ЛР № 1 | E7: не входить у Revenue і COGS
A8: A7 | B8: Сценарії | C8: 70%, 100%, 140% від 85 будівель; mix, usage і ціни сталі | D8: Д: методичка, розділ 3.2 | E8: Revenue, COGS
A9: A8 | B9: Готовність платити за будівлю | C9: 130...135 EUR на місяць за будівлю, не більше 15% цінності 900 EUR | D9: П: гіпотеза A2 ЛР № 1, листами про намір не перевірена | E9: Revenue, GM
A10: A9 | B10: Стаціонарний стан доплати за нестабільний облік | C10: у сценаріях Y3 усі будівлі зі статусом «нестабільний облік» уже пройшли 2 місяці спостереження і 1 пільговий місяць; епізод нестабільності триває 12 місяців | D10: П: спрощення; вплив від 1 до 3 неоплачених місяців наведено в додатку | E10: Revenue overage, GM

Sheet Моделі
A1: Модель | B1: Pricing metric | C1: Передбачуваність доходу | D1: Захист від надмірного використання | E1: Простота продажу | F1: Відповідність цінності | G1: Вимірюваність metric у межах MVP | H1: Оцінка 1...5 | I1: Ранг
A2: Hybrid base + usage (задана) | B2: клієнт (база) і активна будівля за місяць (usage) | C2: 4 | D2: 4 | E2: 3 | F2: 4 | G2: 5 | H2: =AVERAGE(C2:G2) | I2: =RANK(H2,$H$2:$H$4)
A3: Альтернатива 1: фіксована підписка на клієнта | B3: клієнт (акаунт) без ліміту будівель у тарифі | C3: 5 | D3: 2 | E3: 5 | F3: 2 | G3: 5 | H3: =AVERAGE(C3:G3) | I3: =RANK(H3,$H$2:$H$4)
A4: Альтернатива 2: частка підтвердженої економії (gain-sharing) | B4: EUR підтвердженої економії енергії за IPMVP | C4: 1 | D4: 2 | E4: 2 | F4: 5 | G4: 1 | H4: =AVERAGE(C4:G4) | I4: =RANK(H4,$H$2:$H$4)

Sheet Тарифи
A1: Показник | B1: Формула або підстава | C1: Basic | D1: Standard | E1: Pro
A2: Базовий платіж на клієнта, EUR/міс. | B2: вхід | C2: 25 | D2: 50 | E2: 150
A3: Ціна за активну будівлю, EUR/міс. | B3: вхід | C3: 110 | D3: 110 | E3: 90
A4: Максимум будівель у тарифі | B4: захисне правило | C4: 2 | D4: 5 | E4: 20
A5: Частка клієнтів (A1) | B5: A1 | C5: 0.6 | D5: 0.3 | E5: 0.1
A6: Середнє usage, будівель на клієнта (A2) | B6: A2 | C6: 1 | D6: 2 | E6: 5
A7: Год підтримки на клієнта (A4) | B7: A4 | C7: 0.1 | D7: 0.2 | E7: 0.5
A8: COGS на клієнта (база), EUR | B8: год × 30 | C8: =C7*x4_sup_rate | D8: =D7*x4_sup_rate | E8: =E7*x4_sup_rate
A9: Очікуваний рахунок клієнта, EUR/міс. | B9: база + ціна × usage | C9: =C2+C3*C6 | D9: =D2+D3*D6 | E9: =E2+E3*E6
A10: Очікуваний COGS клієнта, EUR/міс. | B10: COGS бази + usage × 16 | C10: =C8+C6*x4_cogs | D10: =D8+D6*x4_cogs | E10: =E8+E6*x4_cogs
A11: Gross profit, EUR/міс. | B11: рахунок мінус COGS | C11: =C9-C10 | D11: =D9-D10 | E11: =E9-E10
A12: Gross margin | B12: (Revenue − COGS) / Revenue | C12: =(C9-C10)/C9 | D12: =(D9-D10)/D9 | E12: =(E9-E10)/E9
A13: Floor price пакета, EUR/міс. | B13: COGS / (1 − 0,70) | C13: =C10/(1-x4_gm) | D13: =D10/(1-x4_gm) | E13: =E10/(1-x4_gm)
A14: Ціна не нижча за floor | B14: порівняння | C14: =IF(C9>=C13,"так","ні") | D14: =IF(D9>=D13,"так","ні") | E14: =IF(E9>=E13,"так","ні")
A15: Markup на COGS | B15: (ціна − COGS) / COGS | C15: =(C9-C10)/C10 | D15: =(D9-D10)/D10 | E15: =(E9-E10)/E10
A16: Ціна на будівлю, EUR | B16: рахунок / usage | C16: =C9/C6 | D16: =D9/D6 | E16: =E9/E6
A17: Частка цінності 900 EUR | B17: ціна будівлі / цінність | C17: =C16/x4_value | D17: =D16/x4_value | E17: =E16/x4_value
A18: Ціна будівлі не нижча за floor одиниці | B18: ціна будівлі ≥ 53,33 | C18: =IF(C3>=x4_floor_unit,"так","ні") | D18: =IF(D3>=x4_floor_unit,"так","ні") | E18: =IF(E3>=x4_floor_unit,"так","ні")
A19: Частка COGS бази в COGS клієнта | B19: COGS бази / COGS клієнта | C19: =C8/C10 | D19: =D8/D10 | E19: =E8/E10
A20: Очікуваний COGS будівлі з A3, EUR | B20: 0,9 × 16 + 0,1 × 30,88 | C20: =(1-x4_high_share)*x4_cogs+x4_high_share*x4_cogs_high | D20: =(1-x4_high_share)*x4_cogs+x4_high_share*x4_cogs_high | E20: =(1-x4_high_share)*x4_cogs+x4_high_share*x4_cogs_high
A21: Очікуваний COGS клієнта з A3, EUR/міс. | B21: COGS бази + usage × 17,49 | C21: =C8+C6*C20 | D21: =D8+D6*D20 | E21: =E8+E6*E20
A22: Очікуваний overage з A3, EUR/міс. | B22: usage × 0,10 × 55 | C22: =C6*x4_high_share*x4_over | D22: =D6*x4_high_share*x4_over | E22: =E6*x4_high_share*x4_over
A23: Очікуваний рахунок з A3, EUR/міс. | B23: рахунок + overage | C23: =C9+C22 | D23: =D9+D22 | E23: =E9+E22
A24: Gross margin з A3 | B24: (Revenue − COGS) / Revenue | C24: =(C23-C21)/C23 | D24: =(D23-D21)/D23 | E24: =(E23-E21)/E23
A26: Перевірка формули floor | B26: Значення, EUR | C26: GM
A27: Правильно: COGS / (1 − GM) | B27: =x4_cogs_var/(1-x4_gm) | C27: =(B27-x4_cogs_var)/B27
A28: Помилково: COGS × (1 + GM) | B28: =x4_cogs_var*(1+x4_gm) | C28: =(B28-x4_cogs_var)/B28
A30: Зважена за A1 gross margin | B30: Значення
A31: Типова будівля, без A3 | B31: =(x4_mix_B*(C9-C10)+x4_mix_S*(D9-D10)+x4_mix_P*(E9-E10))/(x4_mix_B*C9+x4_mix_S*D9+x4_mix_P*E9)
A32: З урахуванням A3, дорівнює GM сценаріїв | B32: =(x4_mix_B*(C23-C21)+x4_mix_S*(D23-D21)+x4_mix_P*(E23-E21))/(x4_mix_B*C23+x4_mix_S*D23+x4_mix_P*E23)

Sheet High usage
A1: Показник | B1: Формула | C1: Basic | D1: Standard | E1: Pro
A2: Будівель у клієнта з high usage | B2: максимум тарифу | C2: 2 | D2: 5 | E2: 20
A3: Рахунок без захисного правила, EUR | B3: база + ціна × n | C3: ='Тарифи'!C2+'Тарифи'!C3*C2 | D3: ='Тарифи'!D2+'Тарифи'!D3*D2 | E3: ='Тарифи'!E2+'Тарифи'!E3*E2
A4: COGS, EUR | B4: COGS бази + n × COGS high | C4: ='Тарифи'!C8+C2*x4_cogs_high | D4: ='Тарифи'!D8+D2*x4_cogs_high | E4: ='Тарифи'!E8+E2*x4_cogs_high
A5: Gross margin без правила | C5: =(C3-C4)/C3 | D5: =(D3-D4)/D3 | E5: =(E3-E4)/E3
A6: Overage за правилом, EUR | B6: n × (доплата + SMS) | C6: =C2*x4_over | D6: =D2*x4_over | E6: =E2*x4_over
A7: Рахунок з правилом, EUR | C7: =C3+C6 | D7: =D3+D6 | E7: =E3+E6
A8: Gross margin з правилом | C8: =(C7-C4)/C7 | D8: =(D7-D4)/D7 | E8: =(E7-E4)/E7
A9: Межа 70% виконана без правила | C9: =IF(C5>=x4_gm,"так","ні") | D9: =IF(D5>=x4_gm,"так","ні") | E9: =IF(E5>=x4_gm,"так","ні")
A10: Межа 70% виконана з правилом | C10: =IF(C8>=x4_gm,"так","ні") | D10: =IF(D8>=x4_gm,"так","ні") | E10: =IF(E8>=x4_gm,"так","ні")
A12: Неоплачених місяців з 12 (A9) | B12: Формула | C12: 0 | D12: 1 | E12: 2 | F12: 3
A13: Overage, базовий сценарій, EUR | B13: overage − буд. high × 50 × m / 12 | C13: ='Сценарії'!$C$12-'Сценарії'!$C$11*x4_fee*C12/x4_episode | D13: ='Сценарії'!$C$12-'Сценарії'!$C$11*x4_fee*D12/x4_episode | E13: ='Сценарії'!$C$12-'Сценарії'!$C$11*x4_fee*E12/x4_episode | F13: ='Сценарії'!$C$12-'Сценарії'!$C$11*x4_fee*F12/x4_episode
A14: Revenue, базовий сценарій, EUR | B14: Revenue − та сама втрата | C14: ='Сценарії'!$C$13-'Сценарії'!$C$11*x4_fee*C12/x4_episode | D14: ='Сценарії'!$C$13-'Сценарії'!$C$11*x4_fee*D12/x4_episode | E14: ='Сценарії'!$C$13-'Сценарії'!$C$11*x4_fee*E12/x4_episode | F14: ='Сценарії'!$C$13-'Сценарії'!$C$11*x4_fee*F12/x4_episode
A15: Gross margin, базовий сценарій | B15: (Revenue − COGS) / Revenue | C15: =(C14-'Сценарії'!$C$16)/C14 | D15: =(D14-'Сценарії'!$C$16)/D14 | E15: =(E14-'Сценарії'!$C$16)/E14 | F15: =(F14-'Сценарії'!$C$16)/F14
A16: GM Pro, 20 буд., неоплачений місяць | B16: рахунок без доплати | C16: =($E$7-$E$2*x4_fee-$E$4)/($E$7-$E$2*x4_fee) | D16: =($E$7-$E$2*x4_fee-$E$4)/($E$7-$E$2*x4_fee) | E16: =($E$7-$E$2*x4_fee-$E$4)/($E$7-$E$2*x4_fee) | F16: =($E$7-$E$2*x4_fee-$E$4)/($E$7-$E$2*x4_fee)
A17: GM Pro, 20 буд., за 12 місяців | B17: зважено за місяцями | C17: =($E$7*(x4_episode-C12)+($E$7-$E$2*x4_fee)*C12-x4_episode*$E$4)/($E$7*(x4_episode-C12)+($E$7-$E$2*x4_fee)*C12) | D17: =($E$7*(x4_episode-D12)+($E$7-$E$2*x4_fee)*D12-x4_episode*$E$4)/($E$7*(x4_episode-D12)+($E$7-$E$2*x4_fee)*D12) | E17: =($E$7*(x4_episode-E12)+($E$7-$E$2*x4_fee)*E12-x4_episode*$E$4)/($E$7*(x4_episode-E12)+($E$7-$E$2*x4_fee)*E12) | F17: =($E$7*(x4_episode-F12)+($E$7-$E$2*x4_fee)*F12-x4_episode*$E$4)/($E$7*(x4_episode-F12)+($E$7-$E$2*x4_fee)*F12)

Sheet Сценарії
A1: Показник за місяць, EUR | B1: Низький 70% | C1: Базовий 100% | D1: Високий 140%
A2: Коефіцієнт масштабу | B2: 0.7 | C2: 1 | D2: 1.4
A3: Платні будівлі (billable units) | B3: =x4_scale*B2 | C3: =x4_scale*C2 | D3: =x4_scale*D2
A4: Середнє usage, будівель на клієнта | B4: =x4_mix_B*x4_use_B+x4_mix_S*x4_use_S+x4_mix_P*x4_use_P | C4: =x4_mix_B*x4_use_B+x4_mix_S*x4_use_S+x4_mix_P*x4_use_P | D4: =x4_mix_B*x4_use_B+x4_mix_S*x4_use_S+x4_mix_P*x4_use_P
A5: Платні клієнти | B5: =B3/B4 | C5: =C3/C4 | D5: =D3/D4
A6: Клієнти Basic | B6: =B5*x4_mix_B | C6: =C5*x4_mix_B | D6: =D5*x4_mix_B
A7: Клієнти Standard | B7: =B5*x4_mix_S | C7: =C5*x4_mix_S | D7: =D5*x4_mix_S
A8: Клієнти Pro | B8: =B5*x4_mix_P | C8: =C5*x4_mix_P | D8: =D5*x4_mix_P
A9: Revenue: базові платежі | B9: =B6*x4_base_B+B7*x4_base_S+B8*x4_base_P | C9: =C6*x4_base_B+C7*x4_base_S+C8*x4_base_P | D9: =D6*x4_base_B+D7*x4_base_S+D8*x4_base_P
A10: Revenue: будівлі (usage) | B10: =B6*x4_use_B*x4_pb_B+B7*x4_use_S*x4_pb_S+B8*x4_use_P*x4_pb_P | C10: =C6*x4_use_B*x4_pb_B+C7*x4_use_S*x4_pb_S+C8*x4_use_P*x4_pb_P | D10: =D6*x4_use_B*x4_pb_B+D7*x4_use_S*x4_pb_S+D8*x4_use_P*x4_pb_P
A11: Будівлі з high usage | B11: =B3*x4_high_share | C11: =C3*x4_high_share | D11: =D3*x4_high_share
A12: Revenue: overage | B12: =B11*x4_over | C12: =C11*x4_over | D12: =D11*x4_over
A13: Revenue | B13: =B9+B10+B12 | C13: =C9+C10+C12 | D13: =D9+D10+D12
A14: COGS: база клієнтів | B14: =B6*x4_cc_B+B7*x4_cc_S+B8*x4_cc_P | C14: =C6*x4_cc_B+C7*x4_cc_S+C8*x4_cc_P | D14: =D6*x4_cc_B+D7*x4_cc_S+D8*x4_cc_P
A15: COGS: будівлі | B15: =(B3-B11)*x4_cogs+B11*x4_cogs_high | C15: =(C3-C11)*x4_cogs+C11*x4_cogs_high | D15: =(D3-D11)*x4_cogs+D11*x4_cogs_high
A16: COGS | B16: =B14+B15 | C16: =C14+C15 | D16: =D14+D15
A17: Gross profit | B17: =B13-B16 | C17: =C13-C16 | D17: =D13-D16
A18: Gross margin | B18: =B17/B13 | C18: =C17/C13 | D18: =D17/D13
A19: ARPA, EUR на клієнта | B19: =B13/B5 | C19: =C13/C5 | D19: =D13/D5
A20: Revenue на будівлю | B20: =B13/B3 | C20: =C13/C3 | D20: =D13/D3
