Workbook
Name x_start: 'Параметри ЛР3'!$C$2
Name x_bl_days: 'Параметри ЛР3'!$C$3
Name x_ef11: 'Параметри ЛР3'!$C$4
Name x_ef12: 'Параметри ЛР3'!$C$5
Name x_fc: 'Параметри ЛР3'!$C$6
Name x_mr_days: 'Параметри ЛР3'!$C$7
Name x_rate_BA: 'Параметри ЛР3'!$C$8
Name x_rate_UX: 'Параметри ЛР3'!$C$9
Name x_rate_DEV: 'Параметри ЛР3'!$C$10
Name x_rate_QA: 'Параметри ЛР3'!$C$11
Name x_rate_OPS: 'Параметри ЛР3'!$C$12
Name x_esv: 'Параметри ЛР3'!$C$13
Name x_min_wage: 'Параметри ЛР3'!$C$14
Name x_cap_mult: 'Параметри ЛР3'!$C$15
Name x_fx: 'Параметри ЛР3'!$C$16
Name x_benefits: 'Параметри ЛР3'!$C$17
Name x_overhead: 'Параметри ЛР3'!$C$18
Name x_days_avg: 'Параметри ЛР3'!$C$19
Name x_r1_p: 'Параметри ЛР3'!$C$20
Name x_r1_impact: 'Параметри ЛР3'!$C$21
Name x_r1_month: 'Параметри ЛР3'!$C$22
Name x_r2_p: 'Параметри ЛР3'!$C$23
Name x_r2_days: 'Параметри ЛР3'!$C$24
Name x_r2_turnover: 'Параметри ЛР3'!$C$25
Name x_cloud_y1: 'Параметри ЛР3'!$C$26
Name x_g2: 'Параметри ЛР3'!$C$27
Name x_g3: 'Параметри ЛР3'!$C$28
Name x_alt_start: 'Параметри ЛР3'!$C$29
Name x_alt_op: 'Параметри ЛР3'!$C$30
Name x_alt_month: 'Параметри ЛР3'!$C$31
Name x_sup_ops: 'Параметри ЛР3'!$C$32
Name x_sup_ba: 'Параметри ЛР3'!$C$33
Name x_chg_dev: 'Параметри ЛР3'!$C$34
Name x_chg_qa: 'Параметри ЛР3'!$C$35
Name x_crisk_p: 'Параметри ЛР3'!$C$36
Name x_crisk_s: 'Параметри ЛР3'!$C$37
Name x_arisk_p: 'Параметри ЛР3'!$C$38
Name x_arisk_hw: 'Параметри ЛР3'!$C$39
Name x_arisk_d: 'Параметри ЛР3'!$C$40
Name x_ret_days: 'Параметри ЛР3'!$C$41
Name x_ret_alt: 'Параметри ЛР3'!$C$42
Name x_disc: 'Параметри ЛР3'!$C$43
Name x_holidays: 'Параметри ЛР3'!$A$46:$A$47
Name x_ps_A: 'Календар і фази'!$B$2
Name x_pe_A: 'Календар і фази'!$C$2
Name x_pm_A: 'Календар і фази'!$E$2
Name x_ps_D: 'Календар і фази'!$B$3
Name x_pe_D: 'Календар і фази'!$C$3
Name x_pm_D: 'Календар і фази'!$E$3
Name x_ps_B: 'Календар і фази'!$B$4
Name x_pe_B: 'Календар і фази'!$C$4
Name x_pm_B: 'Календар і фази'!$E$4
Name x_ps_T: 'Календар і фази'!$B$5
Name x_pe_T: 'Календар і фази'!$C$5
Name x_pm_T: 'Календар і фази'!$E$5
Name x_months_total: 'Календар і фази'!$E$6
Name x_labor: Labor!$L$7
Name x_team_month: Labor!$C$11
Name x_base: 'Baseline MVP'!$B$26
Name x_cont: 'Baseline MVP'!$B$27

Sheet Параметри ЛР3
A1: Ім'я | B1: Показник | C1: Значення | D1: Одиниця | E1: Тип | F1: Пояснення
A2: x_start | B2: Старт проєкту | C2: 46328 | D2: дата | E2: Д | F2: ЛР № 2
A3: x_bl_days | B3: Baseline MVP | C3: 132 | D3: роб. днів | E3: Д | F3: ЛР № 2, P80 з contingency
A4: x_ef11 | B4: Кінець аналізу: EF пакета 1.1 | C4: 8.3333333 | D4: роб. днів | E4: Р | F4: ЛР № 2, CPM
A5: x_ef12 | B5: Кінець проєктування: EF пакета 1.2 | C5: 21.666667 | D5: роб. днів | E5: Р | F5: ЛР № 2, CPM
A6: x_fc | B6: Feature complete | C6: 98.166667 | D6: роб. днів | E6: Р | F6: ЛР № 2, віха
A7: x_mr_days | B7: Management reserve за строком | C7: 15 | D7: роб. днів | E7: Д | F7: ЛР № 2
A8: x_rate_BA | B8: Loaded rate BA/PM | C8: 4600 | D8: EUR/міс. | E8: Д | F8: набір B
A9: x_rate_UX | B9: Loaded rate UX | C9: 4300 | D9: EUR/міс. | E9: Д | F9: набір B
A10: x_rate_DEV | B10: Loaded rate Developer | C10: 5700 | D10: EUR/міс. | E10: Д | F10: набір B
A11: x_rate_QA | B11: Loaded rate QA | C11: 4200 | D11: EUR/міс. | E11: Д | F11: набір B
A12: x_rate_OPS | B12: Loaded rate DevOps | C12: 6100 | D12: EUR/міс. | E12: Д | F12: набір B
A13: x_esv | B13: Ставка ЄСВ роботодавця | C13: 0.22 | D13: частка | E13: Д | F13: закон про ЄСВ
... A24: x_r2_days | B24: R2: зсув фінішу | C24: 10 | D24: роб. днів | E24: П | F24: передача знань і онбординг
A25: x_r2_turnover | B25: Річна плинність розробників | C25: 0.25 | D25: частка | E25: П
A26: x_cloud_y1 | B26: Cloud production Y1 | C26: 12000 | D26: EUR/рік | E26: Д | F26: варіант 14
A27: x_g2 | B27: Growth Y2 | C27: 0.2 | D27: частка | E27: Д | F27: варіант 14
A28: x_g3 | B28: Growth Y3 | C28: 0.1 | D28: частка | E28: Д | F28: варіант 14
A29: x_alt_start | B29: Альтернатива: start | C29: 36000 | D29: EUR | E29: Д | F29: варіант 14
A30: x_alt_op | B30: Альтернатива: op | C30: 15000 | D30: EUR/рік | E30: Д | F30: варіант 14
A31: x_alt_month | B31: Місяць start-up альтернативи | C31: 6 | D31: M | E31: П | F31: до релізу
A32: x_sup_ops | B32: Support: FTE DevOps | C32: 0.25 | D32: FTE | E32: П
A33: x_sup_ba | B33: Support: FTE BA/PM | C33: 0.25 | D33: FTE | E33: П
A34: x_chg_dev | B34: Change: FTE Developer | C34: 0.5 | D34: FTE | E34: П
A35: x_chg_qa | B35: Change: FTE QA | C35: 0.25 | D35: FTE | E35: П
A36: x_crisk_p | B36: Cloud risk: імовірність на рік | C36: 0.3 | D36: частка | E36: П
A37: x_crisk_s | B37: Cloud risk: перевищення | C37: 0.2 | D37: частка cloud | E37: П
A38: x_arisk_p | B38: Alt risk: імовірність на рік | C38: 0.1 | D38: частка | E38: П
A39: x_arisk_hw | B39: Alt risk: заміна вузла | C39: 5000 | D39: EUR | E39: П
A40: x_arisk_d | B40: Alt risk: днів DevOps | C40: 10 | D40: днів | E40: П
A41: x_ret_days | B41: Retirement: днів DevOps | C41: 10 | D41: днів | E41: П
A42: x_ret_alt | B42: Retirement альтернативи: демонтаж | C42: 700 | D42: EUR | E42: П
A43: x_disc | B43: Ставка дисконтування | C43: 0.1 | D43: частка | E43: П | F43: довідково
A45: Неробочі дні
A46: 46387
A47: 46388

Sheet Журнал припущень
A1: ID | B1: Припущення | C1: Значення | D1: Тип | E1: Підстава або джерело
A2: A1 | B2: Ставки ролей | C2: набір B: BA/PM 4 600, UX 4 300, Developer 5 700, QA 4 200, DevOps 6 100 EUR/міс. | D2: Д | E2: рядок варіанта 14, набір B
A3: A2 | B3: Склад loaded rate | C3: оклад + ЄСВ 22% (база не більше 20 мінімальних зарплат) + бенефіти 80 + накладні 650 EUR/міс. на FTE | D3: П | E3: штатна модель; накладні включають робоче місце, ноутбук, бухгалтерію, офісне ПЗ
A4: A3 | B4: Курс для бази ЄСВ | C4: 48 UAH за 1 EUR | D4: П | E4: лише для межі бази ЄСВ; модель у EUR
A5: A4 | B5: Тривалість MVP | C5: 132 роб. дні (baseline ЛР № 2), 02.11.2026...06.05.2027 | D5: Д | E5: ЛР № 2, P80 з contingency
A6: A5 | B6: Межі фаз | C6: аналіз 0...8,33; проєктування 8,33...21,67; розроблення 21,67...98,17; тестування і реліз 98,17...132 роб. дня | D6: Р | E6: EF пакетів 1.1, 1.2, віха Feature complete, baseline
A7: A6 | B7: FTE ролей за фазами | C7: розробники 2,0 у всіх фазах; BA/PM, QA, DevOps від 0,25 до 0,75 за піковим тижневим навантаженням WBS | D7: П | E7: округлення вгору до 0,25, не більше FTE ЛР № 2
A8: A7 | B8: Прямі витрати MVP | C8: обладнання 4 000, ліцензії 7 000, cloud розроблення 4 000 EUR | D8: Д | E8: рядок варіанта 14, розподіл за статтями П
A9: A8 | B9: Ризик R1 | C9: 40% × 16 000 EUR, нестабільні лічильники | D9: Д | E9: рядок варіанта 14
A10: A9 | B10: Ризик R2 | C10: 25% × (5 700 + 19 900 × 10 / 21,75) EUR, вибуття розробника | D10: П | E10: річна плинність 25%, 2 розробники, 6,19 міс.
A11: A10 | B11: Cloud production | C11: Y1 12 000 EUR; Y2 +20%; Y3 +10% | D11: Д | E11: рядок варіанта 14; growth моделює зростання використання
A12: A11 | B12: Альтернатива | C12: fixed hosting у колокації: start 36 000 EUR, op 15 000 EUR на рік | D12: Д | E12: рядок варіанта 14, розподіл за статтями П
... A16: A15 | B16: Інфляція і горизонт | C16: постійні ціни EUR, без індексації; 3 роки експлуатації після релізу | D16: П | E16: однаково для обох сценаріїв

Sheet Ставки
A1: Роль | B1: Loaded rate | C1: Накладні | D1: Бенефіти | E1: Оклад | F1: ЄСВ | G1: Сума складових | H1: Частка окладу | I1: Контроль
A2: BA/PM | B2: =x_rate_BA | C2: =x_overhead | D2: =x_benefits | E2: =IF((B2-C2-D2)/(1+x_esv)<=$B$9,(B2-C2-D2)/(1+x_esv),(B2-C2-D2)-x_esv*$B$9) | F2: =x_esv*MIN(E2,$B$9) | G2: =C2+D2+E2+F2 | H2: =E2/B2 | I2: =IF(ABS(G2-B2)<0.01,"збігається","розбіжність")
A3: UX | B3: =x_rate_UX | C3: =x_overhead | D3: =x_benefits | E3: =IF((B3-C3-D3)/(1+x_esv)<=$B$9,(B3-C3-D3)/(1+x_esv),(B3-C3-D3)-x_esv*$B$9) | F3: =x_esv*MIN(E3,$B$9) | G3: =C3+D3+E3+F3 | H3: =E3/B3 | I3: =IF(ABS(G3-B3)<0.01,"збігається","розбіжність")
A4: Developer | B4: =x_rate_DEV | C4: =x_overhead | D4: =x_benefits | E4: =IF((B4-C4-D4)/(1+x_esv)<=$B$9,(B4-C4-D4)/(1+x_esv),(B4-C4-D4)-x_esv*$B$9) | F4: =x_esv*MIN(E4,$B$9) | G4: =C4+D4+E4+F4 | H4: =E4/B4 | I4: =IF(ABS(G4-B4)<0.01,"збігається","розбіжність")
A5: QA | B5: =x_rate_QA | C5: =x_overhead | D5: =x_benefits | E5: =IF((B5-C5-D5)/(1+x_esv)<=$B$9,(B5-C5-D5)/(1+x_esv),(B5-C5-D5)-x_esv*$B$9) | F5: =x_esv*MIN(E5,$B$9) | G5: =C5+D5+E5+F5 | H5: =E5/B5 | I5: =IF(ABS(G5-B5)<0.01,"збігається","розбіжність")
A6: DevOps | B6: =x_rate_OPS | C6: =x_overhead | D6: =x_benefits | E6: =IF((B6-C6-D6)/(1+x_esv)<=$B$9,(B6-C6-D6)/(1+x_esv),(B6-C6-D6)-x_esv*$B$9) | F6: =x_esv*MIN(E6,$B$9) | G6: =C6+D6+E6+F6 | H6: =E6/B6 | I6: =IF(ABS(G6-B6)<0.01,"збігається","розбіжність")
A8: Показник | B8: Значення
A9: Максимальна база ЄСВ, EUR/міс. | B9: =x_min_wage*x_cap_mult/x_fx

Sheet Календар і фази
A1: Фаза | B1: Початок, роб. день | C1: Кінець, роб. день | D1: Тривалість, роб. днів | E1: Тривалість, міс.
A2: Аналіз | B2: =0 | C2: =x_ef11 | D2: =C2-B2 | E2: =SUM(G9:G20)
A3: Проєктування | B3: =x_ef11 | C3: =x_ef12 | D3: =C3-B3 | E3: =SUM(H9:H20)
A4: Розроблення | B4: =x_ef12 | C4: =x_fc | D4: =C4-B4 | E4: =SUM(I9:I20)
A5: Тестування і реліз | B5: =x_fc | C5: =x_bl_days | D5: =C5-B5 | E5: =SUM(J9:J20)
A6: Разом | D6: =SUM(D2:D5) | E6: =SUM(E2:E5)
A8: Місяць | B8: Початок | C8: Кінець | D8: Роб. днів | E8: Наростом на початок | F8: Наростом на кінець | G8: Частка: аналіз | H8: Частка: проєктування | I8: Частка: розроблення | J8: Частка: тест і реліз | K8: Частка експлуатації
A9: M1 лис 26 | B9: =EDATE(DATE(2026,11,1),0) | C9: =EOMONTH(B9,0) | D9: =NETWORKDAYS(MAX(B9,x_start),C9,x_holidays) | E9: 0 | F9: =E9+D9 | G9: =MAX(0,MIN(x_pe_A,F9)-MAX(x_ps_A,E9))/D9 | H9: =MAX(0,MIN(x_pe_D,F9)-MAX(x_ps_D,E9))/D9 | I9: =MAX(0,MIN(x_pe_B,F9)-MAX(x_ps_B,E9))/D9 | J9: =MAX(0,MIN(x_pe_T,F9)-MAX(x_ps_T,E9))/D9 | K9: =IF(F9<=x_bl_days,0,IF(E9>=x_bl_days,1,(F9-x_bl_days)/D9))
A10: M2 гру 26 | B10: =EDATE(DATE(2026,11,1),1) | C10: =EOMONTH(B10,0) | D10: =NETWORKDAYS(MAX(B10,x_start),C10,x_holidays) | E10: =F9 | F10: =E10+D10 | G10: =MAX(0,MIN(x_pe_A,F10)-MAX(x_ps_A,E10))/D10 | H10: =MAX(0,MIN(x_pe_D,F10)-MAX(x_ps_D,E10))/D10 | I10: =MAX(0,MIN(x_pe_B,F10)-MAX(x_ps_B,E10))/D10 | J10: =MAX(0,MIN(x_pe_T,F10)-MAX(x_ps_T,E10))/D10 | K10: =IF(F10<=x_bl_days,0,IF(E10>=x_bl_days,1,(F10-x_bl_days)/D10))
A11: M3 січ 27 | B11: =EDATE(DATE(2026,11,1),2) | C11: =EOMONTH(B11,0) | D11: =NETWORKDAYS(MAX(B11,x_start),C11,x_holidays) | E11: =F10 | F11: =E11+D11 | G11: =MAX(0,MIN(x_pe_A,F11)-MAX(x_ps_A,E11))/D11 | H11: =MAX(0,MIN(x_pe_D,F11)-MAX(x_ps_D,E11))/D11 | I11: =MAX(0,MIN(x_pe_B,F11)-MAX(x_ps_B,E11))/D11 | J11: =MAX(0,MIN(x_pe_T,F11)-MAX(x_ps_T,E11))/D11 | K11: =IF(F11<=x_bl_days,0,IF(E11>=x_bl_days,1,(F11-x_bl_days)/D11))
A12: M4 лют 27 | B12: =EDATE(DATE(2026,11,1),3) | C12: =EOMONTH(B12,0) | D12: =NETWORKDAYS(MAX(B12,x_start),C12,x_holidays) | E12: =F11 | F12: =E12+D12 | G12: =MAX(0,MIN(x_pe_A,F12)-MAX(x_ps_A,E12))/D12 | H12: =MAX(0,MIN(x_pe_D,F12)-MAX(x_ps_D,E12))/D12 | I12: =MAX(0,MIN(x_pe_B,F12)-MAX(x_ps_B,E12))/D12 | J12: =MAX(0,MIN(x_pe_T,F12)-MAX(x_ps_T,E12))/D12 | K12: =IF(F12<=x_bl_days,0,IF(E12>=x_bl_days,1,(F12-x_bl_days)/D12))
A13: M5 бер 27 | B13: =EDATE(DATE(2026,11,1),4) | C13: =EOMONTH(B13,0) | D13: =NETWORKDAYS(MAX(B13,x_start),C13,x_holidays) | E13: =F12 | F13: =E13+D13 | G13: =MAX(0,MIN(x_pe_A,F13)-MAX(x_ps_A,E13))/D13 | H13: =MAX(0,MIN(x_pe_D,F13)-MAX(x_ps_D,E13))/D13 | I13: =MAX(0,MIN(x_pe_B,F13)-MAX(x_ps_B,E13))/D13 | J13: =MAX(0,MIN(x_pe_T,F13)-MAX(x_ps_T,E13))/D13 | K13: =IF(F13<=x_bl_days,0,IF(E13>=x_bl_days,1,(F13-x_bl_days)/D13))
A14: M6 кві 27 | B14: =EDATE(DATE(2026,11,1),5) | C14: =EOMONTH(B14,0) | D14: =NETWORKDAYS(MAX(B14,x_start),C14,x_holidays) | E14: =F13 | F14: =E14+D14 | G14: =MAX(0,MIN(x_pe_A,F14)-MAX(x_ps_A,E14))/D14 | H14: =MAX(0,MIN(x_pe_D,F14)-MAX(x_ps_D,E14))/D14 | I14: =MAX(0,MIN(x_pe_B,F14)-MAX(x_ps_B,E14))/D14 | J14: =MAX(0,MIN(x_pe_T,F14)-MAX(x_ps_T,E14))/D14 | K14: =IF(F14<=x_bl_days,0,IF(E14>=x_bl_days,1,(F14-x_bl_days)/D14))
A15: M7 тра 27 | B15: =EDATE(DATE(2026,11,1),6) | C15: =EOMONTH(B15,0) | D15: =NETWORKDAYS(MAX(B15,x_start),C15,x_holidays) | E15: =F14 | F15: =E15+D15 | G15: =MAX(0,MIN(x_pe_A,F15)-MAX(x_ps_A,E15))/D15 | H15: =MAX(0,MIN(x_pe_D,F15)-MAX(x_ps_D,E15))/D15 | I15: =MAX(0,MIN(x_pe_B,F15)-MAX(x_ps_B,E15))/D15 | J15: =MAX(0,MIN(x_pe_T,F15)-MAX(x_ps_T,E15))/D15 | K15: =IF(F15<=x_bl_days,0,IF(E15>=x_bl_days,1,(F15-x_bl_days)/D15))
A16: M8 чер 27 | B16: =EDATE(DATE(2026,11,1),7) | C16: =EOMONTH(B16,0) | D16: =NETWORKDAYS(MAX(B16,x_start),C16,x_holidays) | E16: =F15 | F16: =E16+D16 | G16: =MAX(0,MIN(x_pe_A,F16)-MAX(x_ps_A,E16))/D16 | H16: =MAX(0,MIN(x_pe_D,F16)-MAX(x_ps_D,E16))/D16 | I16: =MAX(0,MIN(x_pe_B,F16)-MAX(x_ps_B,E16))/D16 | J16: =MAX(0,MIN(x_pe_T,F16)-MAX(x_ps_T,E16))/D16 | K16: =IF(F16<=x_bl_days,0,IF(E16>=x_bl_days,1,(F16-x_bl_days)/D16))
A17: M9 лип 27 | B17: =EDATE(DATE(2026,11,1),8) | C17: =EOMONTH(B17,0) | D17: =NETWORKDAYS(MAX(B17,x_start),C17,x_holidays) | E17: =F16 | F17: =E17+D17 | G17: =MAX(0,MIN(x_pe_A,F17)-MAX(x_ps_A,E17))/D17 | H17: =MAX(0,MIN(x_pe_D,F17)-MAX(x_ps_D,E17))/D17 | I17: =MAX(0,MIN(x_pe_B,F17)-MAX(x_ps_B,E17))/D17 | J17: =MAX(0,MIN(x_pe_T,F17)-MAX(x_ps_T,E17))/D17 | K17: =IF(F17<=x_bl_days,0,IF(E17>=x_bl_days,1,(F17-x_bl_days)/D17))
A18: M10 сер 27 | B18: =EDATE(DATE(2026,11,1),9) | C18: =EOMONTH(B18,0) | D18: =NETWORKDAYS(MAX(B18,x_start),C18,x_holidays) | E18: =F17 | F18: =E18+D18 | G18: =MAX(0,MIN(x_pe_A,F18)-MAX(x_ps_A,E18))/D18 | H18: =MAX(0,MIN(x_pe_D,F18)-MAX(x_ps_D,E18))/D18 | I18: =MAX(0,MIN(x_pe_B,F18)-MAX(x_ps_B,E18))/D18 | J18: =MAX(0,MIN(x_pe_T,F18)-MAX(x_ps_T,E18))/D18 | K18: =IF(F18<=x_bl_days,0,IF(E18>=x_bl_days,1,(F18-x_bl_days)/D18))
A19: M11 вер 27 | B19: =EDATE(DATE(2026,11,1),10) | C19: =EOMONTH(B19,0) | D19: =NETWORKDAYS(MAX(B19,x_start),C19,x_holidays) | E19: =F18 | F19: =E19+D19 | G19: =MAX(0,MIN(x_pe_A,F19)-MAX(x_ps_A,E19))/D19 | H19: =MAX(0,MIN(x_pe_D,F19)-MAX(x_ps_D,E19))/D19 | I19: =MAX(0,MIN(x_pe_B,F19)-MAX(x_ps_B,E19))/D19 | J19: =MAX(0,MIN(x_pe_T,F19)-MAX(x_ps_T,E19))/D19 | K19: =IF(F19<=x_bl_days,0,IF(E19>=x_bl_days,1,(F19-x_bl_days)/D19))
A20: M12 жов 27 | B20: =EDATE(DATE(2026,11,1),11) | C20: =EOMONTH(B20,0) | D20: =NETWORKDAYS(MAX(B20,x_start),C20,x_holidays) | E20: =F19 | F20: =E20+D20 | G20: =MAX(0,MIN(x_pe_A,F20)-MAX(x_ps_A,E20))/D20 | H20: =MAX(0,MIN(x_pe_D,F20)-MAX(x_ps_D,E20))/D20 | I20: =MAX(0,MIN(x_pe_B,F20)-MAX(x_ps_B,E20))/D20 | J20: =MAX(0,MIN(x_pe_T,F20)-MAX(x_ps_T,E20))/D20 | K20: =IF(F20<=x_bl_days,0,IF(E20>=x_bl_days,1,(F20-x_bl_days)/D20))

Sheet Labor
A1: Роль | B1: Loaded rate, EUR/міс. | C1: FTE: аналіз | D1: FTE: проєктування | E1: FTE: розроблення | F1: FTE: тест і реліз | G1: FTE-міс.: аналіз | H1: FTE-міс.: проєктування | I1: FTE-міс.: розроблення | J1: FTE-міс.: тест і реліз | K1: FTE-міс. разом | L1: Вартість, EUR | M1: FTE у ЛР № 2
A2: BA/PM | B2: =x_rate_BA | C2: 0.5 | D2: 0.25 | E2: 0.5 | F2: 0.5 | G2: =C2*x_pm_A | H2: =D2*x_pm_D | I2: =E2*x_pm_B | J2: =F2*x_pm_T | K2: =SUM(G2:J2) | L2: =B2*K2 | M2: 0.5
A3: UX | B3: =x_rate_UX | C3: 0 | D3: 0 | E3: 0 | F3: 0 | G3: =C3*x_pm_A | H3: =D3*x_pm_D | I3: =E3*x_pm_B | J3: =F3*x_pm_T | K3: =SUM(G3:J3) | L3: =B3*K3 | M3: 0
A4: Developer (2 особи) | B4: =x_rate_DEV | C4: 2 | D4: 2 | E4: 2 | F4: 2 | G4: =C4*x_pm_A | H4: =D4*x_pm_D | I4: =E4*x_pm_B | J4: =F4*x_pm_T | K4: =SUM(G4:J4) | L4: =B4*K4 | M4: 2
A5: QA | B5: =x_rate_QA | C5: 0.25 | D5: 0.5 | E5: 0.75 | F5: 0.75 | G5: =C5*x_pm_A | H5: =D5*x_pm_D | I5: =E5*x_pm_B | J5: =F5*x_pm_T | K5: =SUM(G5:J5) | L5: =B5*K5 | M5: 0.75
A6: DevOps | B6: =x_rate_OPS | C6: 0.25 | D6: 0.5 | E6: 0.5 | F6: 0.5 | G6: =C6*x_pm_A | H6: =D6*x_pm_D | I6: =E6*x_pm_B | J6: =F6*x_pm_T | K6: =SUM(G6:J6) | L6: =B6*K6 | M6: 0.5
A7: Разом | C7: =SUM(C2:C6) | D7: =SUM(D2:D6) | E7: =SUM(E2:E6) | F7: =SUM(F2:F6) | G7: =SUM(G2:G6) | H7: =SUM(H2:H6) | I7: =SUM(I2:I6) | J7: =SUM(J2:J6) | ... M7: =SUM(M2:M6)
A9: Вартість команди за повний місяць фази | C9: =SUMPRODUCT($B$2:$B$6,C2:C6) | D9: =SUMPRODUCT($B$2:$B$6,D2:D6) | E9: =SUMPRODUCT($B$2:$B$6,E2:E6) | F9: =SUMPRODUCT($B$2:$B$6,F2:F6)
A10: Вартість фази, EUR | C10: =SUMPRODUCT($B$2:$B$6,G2:G6) | D10: =SUMPRODUCT($B$2:$B$6,H2:H6) | E10: =SUMPRODUCT($B$2:$B$6,I2:I6) | F10: =SUMPRODUCT($B$2:$B$6,J2:J6)
A11: Команда за FTE ЛР № 2, EUR/міс. | C11: =SUMPRODUCT($B$2:$B$6,$M$2:$M$6)

Sheet Baseline MVP
A1: Стаття | B1: Позиція | C1: Місяць | D1: Сума, EUR
A2: Обладнання | B2: Прототип шлюзу: мінікомп'ютер, адаптер RS-485, LTE модем, 3 лічильники | C2: 1 | D2: 1200
A3: Обладнання | B3: Тест-стенд: 6 типів лічильників, імітатор обривів | C3: 2 | D3: 2000
A4: Обладнання | B4: Шлюз і монтажні матеріали пілотної будівлі | C4: 4 | D4: 800
A5: Ліцензії | B5: Інструменти розробки, репозиторій, трекер задач і CI на 5 осіб | C5: 1 | D5: 2500
A6: Ліцензії | B6: ПЗ тест-стенда: аналізатор і симулятор Modbus | C6: 2 | D6: 1500
A7: Ліцензії | B7: Бібліотека графіків дашборда, комерційна ліцензія | C7: 4 | D7: 1000
A8: Ліцензії | B8: Навантажувальне і безпекове тестування: хмарний сервіс k6 і сканер вразливостей | C8: 6 | D8: 2000
A9: Cloud розроблення | B9: dev і stage, CI, тестовий брокер | C9: 1 | D9: 200
A10: Cloud розроблення | B10: dev і stage, CI, тестовий брокер | C10: 2 | D10: 400
A11: Cloud розроблення | B11: dev і stage, CI, тестовий брокер | C11: 3 | D11: 600
A12: Cloud розроблення | B12: dev і stage, CI, тестовий брокер | C12: 4 | D12: 600
A13: Cloud розроблення | B13: dev і stage, CI, тестовий брокер | C13: 5 | D13: 800
... A15: Cloud розроблення | B15: dev і stage, CI, тестовий брокер | C15: 7 | D15: 400
A17: ID | B17: Ризик | C17: Імовірність | D17: Вплив, EUR | E17: EMV, EUR | F17: Місяць реакції | G17: Довідково
A18: R1 | B18: Нестабільні лічильники (варіант) | C18: =x_r1_p | D18: =x_r1_impact | E18: =C18*D18 | F18: =x_r1_month | G18: =x_team_month*x_mr_days/x_days_avg
A19: R2 | B19: Вибуття розробника | C19: =x_r2_p | D19: =x_rate_DEV+x_team_month*x_r2_days/x_days_avg | E19: =C19*D19 | F19: немає | G19: =1-(1-x_r2_turnover)^(2*x_months_total/12)
A21: Стаття | B21: Сума, EUR | C21: Додаємо окремо? | D21: Підстава
A22: Loaded labor | B22: =x_labor | C22: ні, базова стаття | D22: аркуш Labor
A23: Обладнання | B23: =SUMIF(A2:A15,"Обладнання",D2:D15) | C23: так, не входить у ставку | D23: варіант 14
A24: Ліцензії | B24: =SUMIF(A2:A15,"Ліцензії",D2:D15) | C24: так, не входить у ставку | D24: варіант 14
A25: Cloud розроблення | B25: =SUMIF(A2:A15,"Cloud розроблення",D2:D15) | C25: так | D25: варіант 14
A26: Base cost estimate MVP | B26: =SUM(B22:B25) | D26: labor + прямі
A27: Contingency | B27: =SUM(E18:E19) | C27: так | D27: EMV R1 + EMV R2
A28: Cost baseline MVP | B28: =B26+B27 | D28: base estimate + contingency
A29: Management reserve | B29: =D18-E18 | C29: окремо | D29: R1: вплив мінус EMV
A30: Project budget | B30: =B28+B29 | D30: cost baseline + MR

Sheet Cash burn
A1: Стаття, EUR | B1: M1 лис 26 | C1: M2 гру 26 | D1: M3 січ 27 | E1: M4 лют 27 | F1: M5 бер 27 | G1: M6 кві 27 | H1: M7 тра 27 | I1: M8 чер 27 | J1: M9 лип 27 | K1: M10 сер 27 | L1: M11 вер 27 | M1: M12 жов 27 | N1: Разом
A2: Labor MVP | B2: =SUMPRODUCT('Календар і фази'!G9:J9,Labor!$C$9:$F$9) | C2: =SUMPRODUCT('Календар і фази'!G10:J10,Labor!$C$9:$F$9) | D2: =SUMPRODUCT('Календар і фази'!G11:J11,Labor!$C$9:$F$9) | E2: =SUMPRODUCT('Календар і фази'!G12:J12,Labor!$C$9:$F$9) | F2: =SUMPRODUCT('Календар і фази'!G13:J13,Labor!$C$9:$F$9) | G2: =SUMPRODUCT('Календар і фази'!G14:J14,Labor!$C$9:$F$9) | H2: =SUMPRODUCT('Календар і фази'!G15:J15,Labor!$C$9:$F$9) | I2: =SUMPRODUCT('Календар і фази'!G16:J16,Labor!$C$9:$F$9) | J2: =SUMPRODUCT('Календар і фази'!G17:J17,Labor!$C$9:$F$9) | K2: =SUMPRODUCT('Календар і фази'!G18:J18,Labor!$C$9:$F$9) | L2: =SUMPRODUCT('Календар і фази'!G19:J19,Labor!$C$9:$F$9) | M2: =SUMPRODUCT('Календар і фази'!G20:J20,Labor!$C$9:$F$9) | N2: =SUM(B2:M2)
A3: Обладнання / ліцензії | B3: =SUMIF('Baseline MVP'!$C$2:$C$15,1,'Baseline MVP'!$D$2:$D$15)-SUMIFS('Baseline MVP'!$D$2:$D$15,'Baseline MVP'!$C$2:$C$15,1,'Baseline MVP'!$A$2:$A$15,"Cloud розроблення") | C3: =SUMIF('Baseline MVP'!$C$2:$C$15,2,'Baseline MVP'!$D$2:$D$15)-SUMIFS('Baseline MVP'!$D$2:$D$15,'Baseline MVP'!$C$2:$C$15,2,'Baseline MVP'!$A$2:$A$15,"Cloud розроблення") | D3: =SUMIF('Baseline MVP'!$C$2:$C$15,3,'Baseline MVP'!$D$2:$D$15)-SUMIFS('Baseline MVP'!$D$2:$D$15,'Baseline MVP'!$C$2:$C$15,3,'Baseline MVP'!$A$2:$A$15,"Cloud розроблення") | E3: =SUMIF('Baseline MVP'!$C$2:$C$15,4,'Baseline MVP'!$D$2:$D$15)-SUMIFS('Baseline MVP'!$D$2:$D$15,'Baseline MVP'!$C$2:$C$15,4,'Baseline MVP'!$A$2:$A$15,"Cloud розроблення") | F3: =SUMIF('Baseline MVP'!$C$2:$C$15,5,'Baseline MVP'!$D$2:$D$15)-SUMIFS('Baseline MVP'!$D$2:$D$15,'Baseline MVP'!$C$2:$C$15,5,'Baseline MVP'!$A$2:$A$15,"Cloud розроблення") | G3: =SUMIF('Baseline MVP'!$C$2:$C$15,6,'Baseline MVP'!$D$2:$D$15)-SUMIFS('Baseline MVP'!$D$2:$D$15,'Baseline MVP'!$C$2:$C$15,6,'Baseline MVP'!$A$2:$A$15,"Cloud розроблення") | H3: =SUMIF('Baseline MVP'!$C$2:$C$15,7,'Baseline MVP'!$D$2:$D$15)-SUMIFS('Baseline MVP'!$D$2:$D$15,'Baseline MVP'!$C$2:$C$15,7,'Baseline MVP'!$A$2:$A$15,"Cloud розроблення") | I3: =SUMIF('Baseline MVP'!$C$2:$C$15,8,'Baseline MVP'!$D$2:$D$15)-SUMIFS('Baseline MVP'!$D$2:$D$15,'Baseline MVP'!$C$2:$C$15,8,'Baseline MVP'!$A$2:$A$15,"Cloud розроблення") | J3: =SUMIF('Baseline MVP'!$C$2:$C$15,9,'Baseline MVP'!$D$2:$D$15)-SUMIFS('Baseline MVP'!$D$2:$D$15,'Baseline MVP'!$C$2:$C$15,9,'Baseline MVP'!$A$2:$A$15,"Cloud розроблення") | K3: =SUMIF('Baseline MVP'!$C$2:$C$15,10,'Baseline MVP'!$D$2:$D$15)-SUMIFS('Baseline MVP'!$D$2:$D$15,'Baseline MVP'!$C$2:$C$15,10,'Baseline MVP'!$A$2:$A$15,"Cloud розроблення") | L3: =SUMIF('Baseline MVP'!$C$2:$C$15,11,'Baseline MVP'!$D$2:$D$15)-SUMIFS('Baseline MVP'!$D$2:$D$15,'Baseline MVP'!$C$2:$C$15,11,'Baseline MVP'!$A$2:$A$15,"Cloud розроблення") | M3: =SUMIF('Baseline MVP'!$C$2:$C$15,12,'Baseline MVP'!$D$2:$D$15)-SUMIFS('Baseline MVP'!$D$2:$D$15,'Baseline MVP'!$C$2:$C$15,12,'Baseline MVP'!$A$2:$A$15,"Cloud розроблення") | N3: =SUM(B3:M3)
A4: Cloud розроблення / operation | B4: =SUMIFS('Baseline MVP'!$D$2:$D$15,'Baseline MVP'!$C$2:$C$15,1,'Baseline MVP'!$A$2:$A$15,"Cloud розроблення")+x_cloud_y1/12*'Календар і фази'!K9 | C4: =SUMIFS('Baseline MVP'!$D$2:$D$15,'Baseline MVP'!$C$2:$C$15,2,'Baseline MVP'!$A$2:$A$15,"Cloud розроблення")+x_cloud_y1/12*'Календар і фази'!K10 | D4: =SUMIFS('Baseline MVP'!$D$2:$D$15,'Baseline MVP'!$C$2:$C$15,3,'Baseline MVP'!$A$2:$A$15,"Cloud розроблення")+x_cloud_y1/12*'Календар і фази'!K11 | E4: =SUMIFS('Baseline MVP'!$D$2:$D$15,'Baseline MVP'!$C$2:$C$15,4,'Baseline MVP'!$A$2:$A$15,"Cloud розроблення")+x_cloud_y1/12*'Календар і фази'!K12 | F4: =SUMIFS('Baseline MVP'!$D$2:$D$15,'Baseline MVP'!$C$2:$C$15,5,'Baseline MVP'!$A$2:$A$15,"Cloud розроблення")+x_cloud_y1/12*'Календар і фази'!K13 | G4: =SUMIFS('Baseline MVP'!$D$2:$D$15,'Baseline MVP'!$C$2:$C$15,6,'Baseline MVP'!$A$2:$A$15,"Cloud розроблення")+x_cloud_y1/12*'Календар і фази'!K14 | H4: =SUMIFS('Baseline MVP'!$D$2:$D$15,'Baseline MVP'!$C$2:$C$15,7,'Baseline MVP'!$A$2:$A$15,"Cloud розроблення")+x_cloud_y1/12*'Календар і фази'!K15 | I4: =SUMIFS('Baseline MVP'!$D$2:$D$15,'Baseline MVP'!$C$2:$C$15,8,'Baseline MVP'!$A$2:$A$15,"Cloud розроблення")+x_cloud_y1/12*'Календар і фази'!K16 | J4: =SUMIFS('Baseline MVP'!$D$2:$D$15,'Baseline MVP'!$C$2:$C$15,9,'Baseline MVP'!$A$2:$A$15,"Cloud розроблення")+x_cloud_y1/12*'Календар і фази'!K17 | K4: =SUMIFS('Baseline MVP'!$D$2:$D$15,'Baseline MVP'!$C$2:$C$15,10,'Baseline MVP'!$A$2:$A$15,"Cloud розроблення")+x_cloud_y1/12*'Календар і фази'!K18 | L4: =SUMIFS('Baseline MVP'!$D$2:$D$15,'Baseline MVP'!$C$2:$C$15,11,'Baseline MVP'!$A$2:$A$15,"Cloud розроблення")+x_cloud_y1/12*'Календар і фази'!K19 | M4: =SUMIFS('Baseline MVP'!$D$2:$D$15,'Baseline MVP'!$C$2:$C$15,12,'Baseline MVP'!$A$2:$A$15,"Cloud розроблення")+x_cloud_y1/12*'Календар і фази'!K20 | N4: =SUM(B4:M4)
A5: Support і change після релізу | B5: =(TCO!$H$4+TCO!$H$5)/12*'Календар і фази'!K9 | C5: =(TCO!$H$4+TCO!$H$5)/12*'Календар і фази'!K10 | D5: =(TCO!$H$4+TCO!$H$5)/12*'Календар і фази'!K11 | E5: =(TCO!$H$4+TCO!$H$5)/12*'Календар і фази'!K12 | F5: =(TCO!$H$4+TCO!$H$5)/12*'Календар і фази'!K13 | G5: =(TCO!$H$4+TCO!$H$5)/12*'Календар і фази'!K14 | H5: =(TCO!$H$4+TCO!$H$5)/12*'Календар і фази'!K15 | I5: =(TCO!$H$4+TCO!$H$5)/12*'Календар і фази'!K16 | J5: =(TCO!$H$4+TCO!$H$5)/12*'Календар і фази'!K17 | K5: =(TCO!$H$4+TCO!$H$5)/12*'Календар і фази'!K18 | L5: =(TCO!$H$4+TCO!$H$5)/12*'Календар і фази'!K19 | M5: =(TCO!$H$4+TCO!$H$5)/12*'Календар і фази'!K20 | N5: =SUM(B5:M5)
A6: Використання резерву | B6: =SUMIF('Baseline MVP'!$F$18:$F$19,1,'Baseline MVP'!$E$18:$E$19) | C6: =SUMIF('Baseline MVP'!$F$18:$F$19,2,'Baseline MVP'!$E$18:$E$19) | D6: =SUMIF('Baseline MVP'!$F$18:$F$19,3,'Baseline MVP'!$E$18:$E$19) | E6: =SUMIF('Baseline MVP'!$F$18:$F$19,4,'Baseline MVP'!$E$18:$E$19) | F6: =SUMIF('Baseline MVP'!$F$18:$F$19,5,'Baseline MVP'!$E$18:$E$19) | G6: =SUMIF('Baseline MVP'!$F$18:$F$19,6,'Baseline MVP'!$E$18:$E$19) | H6: =SUMIF('Baseline MVP'!$F$18:$F$19,7,'Baseline MVP'!$E$18:$E$19) | I6: =SUMIF('Baseline MVP'!$F$18:$F$19,8,'Baseline MVP'!$E$18:$E$19) | J6: =SUMIF('Baseline MVP'!$F$18:$F$19,9,'Baseline MVP'!$E$18:$E$19) | K6: =SUMIF('Baseline MVP'!$F$18:$F$19,10,'Baseline MVP'!$E$18:$E$19) | L6: =SUMIF('Baseline MVP'!$F$18:$F$19,11,'Baseline MVP'!$E$18:$E$19) | M6: =SUMIF('Baseline MVP'!$F$18:$F$19,12,'Baseline MVP'!$E$18:$E$19) | N6: =SUM(B6:M6)
A7: Разом cash burn | B7: =SUM(B2:B6) | C7: =SUM(C2:C6) | D7: =SUM(D2:D6) | E7: =SUM(E2:E6) | F7: =SUM(F2:F6) | G7: =SUM(G2:G6) | H7: =SUM(H2:H6) | I7: =SUM(I2:I6) | ... M7: =SUM(M2:M6) | N7: =SUM(B7:M7)
A8: Наростаючим підсумком | B8: =B7 | C8: =B8+C7 | D8: =C8+D7 | E8: =D8+E7 | F8: =E8+F7 | G8: =F8+G7 | H8: =G8+H7 | I8: =H8+I7 | J8: =I8+J7 | ... M8: =L8+M7
A9: Альтернатива: разом cash burn | B9: =B7-x_cloud_y1/12*'Календар і фази'!K9+x_alt_op/12*'Календар і фази'!K9+IF(1=x_alt_month,x_alt_start,0) | C9: =C7-x_cloud_y1/12*'Календар і фази'!K10+x_alt_op/12*'Календар і фази'!K10+IF(2=x_alt_month,x_alt_start,0) | D9: =D7-x_cloud_y1/12*'Календар і фази'!K11+x_alt_op/12*'Календар і фази'!K11+IF(3=x_alt_month,x_alt_start,0) | E9: =E7-x_cloud_y1/12*'Календар і фази'!K12+x_alt_op/12*'Календар і фази'!K12+IF(4=x_alt_month,x_alt_start,0) | F9: =F7-x_cloud_y1/12*'Календар і фази'!K13+x_alt_op/12*'Календар і фази'!K13+IF(5=x_alt_month,x_alt_start,0) | G9: =G7-x_cloud_y1/12*'Календар і фази'!K14+x_alt_op/12*'Календар і фази'!K14+IF(6=x_alt_month,x_alt_start,0) | H9: =H7-x_cloud_y1/12*'Календар і фази'!K15+x_alt_op/12*'Календар і фази'!K15+IF(7=x_alt_month,x_alt_start,0) | I9: =I7-x_cloud_y1/12*'Календар і фази'!K16+x_alt_op/12*'Календар і фази'!K16+IF(8=x_alt_month,x_alt_start,0) | J9: =J7-x_cloud_y1/12*'Календар і фази'!K17+x_alt_op/12*'Календар і фази'!K17+IF(9=x_alt_month,x_alt_start,0) | K9: =K7-x_cloud_y1/12*'Календар і фази'!K18+x_alt_op/12*'Календар і фази'!K18+IF(10=x_alt_month,x_alt_start,0) | L9: =L7-x_cloud_y1/12*'Календар і фази'!K19+x_alt_op/12*'Календар і фази'!K19+IF(11=x_alt_month,x_alt_start,0) | M9: =M7-x_cloud_y1/12*'Календар і фази'!K20+x_alt_op/12*'Календар і фази'!K20+IF(12=x_alt_month,x_alt_start,0) | N9: =SUM(B9:M9)
A11: Показник | B11: Значення
A12: Contingency, EUR | B12: =x_cont
A13: Використано в плані M1...M12, EUR | B13: =N6
A14: Залишок contingency, EUR | B14: =B12-B13
A15: Management reserve (поза baseline), EUR | B15: =x_mr
A16: Місяць релізу | B16: ="M7, "&TEXT(WORKDAY(x_start,x_bl_days-1,x_holidays),"DD.MM.YYYY")

Sheet TCO
A1: Компонент | B1: Cloud Y1 | C1: Cloud Y2 | D1: Cloud Y3 | E1: Альтернатива Y1 | F1: Альтернатива Y2 | G1: Альтернатива Y3 | H1: Річна база | I1: Cloud Σ3 | J1: Альтернатива Σ3
A2: MVP / start-up | B2: =x_cbl | C2: 0 | D2: 0 | E2: =x_cbl+x_alt_start | F2: 0 | G2: 0 | I2: =SUM(B2:D2) | J2: =SUM(E2:G2)
A3: Operation | B3: =x_cloud_y1 | C3: =B3*(1+x_g2) | D3: =C3*(1+x_g3) | E3: =x_alt_op | F3: =x_alt_op | G3: =x_alt_op | I3: =SUM(B3:D3) | J3: =SUM(E3:G3)
A4: Support | B4: =$H$4 | C4: =$H$4 | D4: =$H$4 | E4: =$H$4 | F4: =$H$4 | G4: =$H$4 | H4: =12*(x_sup_ops*x_rate_OPS+x_sup_ba*x_rate_BA) | I4: =SUM(B4:D4) | J4: =SUM(E4:G4)
A5: Change | B5: =$H$5 | C5: =$H$5 | D5: =$H$5 | E5: =$H$5 | F5: =$H$5 | G5: =$H$5 | H5: =12*(x_chg_dev*x_rate_DEV+x_chg_qa*x_rate_QA) | I5: =SUM(B5:D5) | J5: =SUM(E5:G5)
A6: Risk після релізу | B6: =x_crisk_p*x_crisk_s*B3 | C6: =x_crisk_p*x_crisk_s*C3 | D6: =x_crisk_p*x_crisk_s*D3 | E6: =x_arisk_p*(x_arisk_hw+x_arisk_d*x_rate_OPS/x_days_avg) | F6: =x_arisk_p*(x_arisk_hw+x_arisk_d*x_rate_OPS/x_days_avg) | G6: =x_arisk_p*(x_arisk_hw+x_arisk_d*x_rate_OPS/x_days_avg) | I6: =SUM(B6:D6) | J6: =SUM(E6:G6)
A7: Change і risk | B7: =B5+B6 | C7: =C5+C6 | D7: =D5+D6 | E7: =E5+E6 | F7: =F5+F6 | G7: =G5+G6 | I7: =SUM(B7:D7) | J7: =SUM(E7:G7)
A8: Retirement | B8: 0 | C8: 0 | D8: =x_ret_days*x_rate_OPS/x_days_avg | E8: 0 | F8: 0 | G8: =x_ret_days*x_rate_OPS/x_days_avg+x_ret_alt | I8: =SUM(B8:D8) | J8: =SUM(E8:G8)
A9: Разом за рік | B9: =B2+B3+B4+B7+B8 | C9: =C2+C3+C4+C7+C8 | D9: =D2+D3+D4+D7+D8 | E9: =E2+E3+E4+E7+E8 | F9: =F2+F3+F4+F7+F8 | G9: =G2+G3+G4+G7+G8 | I9: =SUM(B9:D9) | J9: =SUM(E9:G9)
A10: TCO3 | D10: =SUM(B9:D9) | G10: =SUM(E9:G9) | I10: =I9 | J10: =J9
A11: Різниця: альтернатива мінус cloud | J11: =J10-I10
A12: PV при ставці дисконтування | D12: =B9+C9/(1+x_disc)+D9/(1+x_disc)^2 | G12: =E9+F9/(1+x_disc)+G9/(1+x_disc)^2
A14: Cloud Y1, множник | B14: Cloud Y1, EUR | C14: TCO3 cloud | D14: TCO3 альтернатива | E14: Різниця | F14: Рішення
A15: 0.8 | B15: =x_cloud_y1*A15 | C15: =x_tco_cloud+(A15-1)*(I3+I6) | D15: =x_tco_alt | E15: =D15-C15 | F15: =IF(E15>0,"cloud","альтернатива")
A16: 1 | B16: =x_cloud_y1*A16 | C16: =x_tco_cloud+(A16-1)*(I3+I6) | D16: =x_tco_alt | E16: =D16-C16 | F16: =IF(E16>0,"cloud","альтернатива")
A17: 1.2 | B17: =x_cloud_y1*A17 | C17: =x_tco_cloud+(A17-1)*(I3+I6) | D17: =x_tco_alt | E17: =D17-C17 | F17: =IF(E17>0,"cloud","альтернатива")
A18: Беззбитковий множник | B18: =(x_tco_alt-(x_tco_cloud-(I3+I6)))/(I3+I6) | C18: =x_cloud_y1*B18
